loralogger/__init__.py
loralogger/filters/__init__.py
loralogger/handlers/__init__.py
loralogger/handlers/log_to_es.py
loralogger/loggers/__init__.py
loralogger/loggers/loralogger.py
loralogger/producer.py
loralogger/utils.py
loralogger-0.2.4.dist-info/WHEEL
loralogger-0.2.4.dist-info/METADATA
loralogger-0.2.4.dist-info/RECORD
