Metadata-Version: 2.1
Name: loralogger
Version: 0.2.4
Summary: Custom logging handler for AskLora projects
License: MIT
Author: LORA Technologies
Author-email: asklora@loratechai.com
Requires-Python: >=3.9,<4.0
Classifier: License :: OSI Approved :: MIT License
Classifier: Programming Language :: Python :: 3
Classifier: Programming Language :: Python :: 3.9
Classifier: Programming Language :: Python :: 3.10
Requires-Dist: WorkerConnector (>=0.0.8,<0.0.9)
Requires-Dist: python-dotenv (>=0.20.0,<0.21.0)
Requires-Dist: redis (>=4.3.4,<5.0.0)
